psvmp/VERSION.py
psvmp/__init__.py
psvmp/gui.py
psvmp/psmedia.py
psvmp/updater.py
psvmp-2.0.1.dist-info/licenses/LICENSE.txt
psvmp-2.0.1.dist-info/METADATA
psvmp-2.0.1.dist-info/WHEEL
psvmp-2.0.1.dist-info/entry_points.txt
psvmp-2.0.1.dist-info/top_level.txt
psvmp-2.0.1.dist-info/RECORD
