Metadata-Version: 2.4
Name: psvmp
Version: 2.0.1
Summary: PS Vita Media Processor - download, convert and transfer media
Home-page: https://github.com/R0salman/PSVMP
Author: 0w0-wz5
Author-email: 0w0-wz5 <salmanalmtyry522@gmail.com>
License: MIT
Project-URL: Homepage, https://github.com/R0salman/PSVMP
Project-URL: Repository, https://github.com/R0salman/PSVMP
Project-URL: Issues, https://github.com/R0salman/PSVMP/issues
Project-URL: Documentation, https://github.com/R0salman/PSVMP#readme
Keywords: psvita,media,converter,download,youtube,soundcloud,mega
Classifier: Development Status :: 5 - Production/Stable
Classifier: Intended Audience :: End Users/Desktop
Classifier: License :: OSI Approved :: MIT License
Classifier: Operating System :: OS Independent
Classifier: Programming Language :: Python :: 3
Classifier: Programming Language :: Python :: 3.8
Classifier: Programming Language :: Python :: 3.9
Classifier: Programming Language :: Python :: 3.10
Classifier: Programming Language :: Python :: 3.11
Classifier: Programming Language :: Python :: 3.12
Classifier: Topic :: Multimedia :: Video :: Conversion
Classifier: Topic :: Multimedia :: Sound/Audio :: Conversion
Requires-Python: >=3.8
License-File: LICENSE.txt
Requires-Dist: tqdm
Requires-Dist: requests
Requires-Dist: PyQt6
Requires-Dist: yt-dlp
Provides-Extra: gui
Requires-Dist: PyQt6; extra == "gui"
Requires-Dist: pyqtdarktheme; extra == "gui"
Requires-Dist: qdarktheme; extra == "gui"
Dynamic: license-file
